singleton_class_decorator/MetaClasses.py
singleton_class_decorator/__init__.py
singleton_class_decorator/singleton.py
singleton_class_decorator/utils.py
singleton_class_decorator-1.0.1.dist-info/LICENSE
singleton_class_decorator-1.0.1.dist-info/METADATA
singleton_class_decorator-1.0.1.dist-info/WHEEL
singleton_class_decorator-1.0.1.dist-info/top_level.txt
singleton_class_decorator-1.0.1.dist-info/RECORD
