Metadata-Version: 2.1
Name: singleton-class-decorator
Version: 1.0.1
Summary: Singleton Class Decorator
Author-email: Jeremy Ribeiro <jeremy.d.ribeiro@gmail.com>
License: MIT License
Project-URL: Homepage, https://github.com/Jrmy-rbr/singleton-class-decorator
Requires-Python: >=3.9
License-File: LICENSE
